<?xml version="1.0" encoding="utf-8"?>
<GameInfo>

	<!--
		Equipment contains both equipment info and Resources-related info.		
		PostUpdate.sql add the required entries or rows to various tables like Types, Resources, or Equipment itself (for the <Name> entry)		
		By default <ResourceClassType> for Equipment is set to "RESOURCECLASS_STRATEGIC"
	-->
	
	<Equipment>  <!-- Materiel is both Equipment and Resource -->
		<Row ResourceType="RESOURCE_MATERIEL" Size="10" />
	</Equipment>
	
	<Equipment> <!-- Melee Weapons -->
		<Row ResourceType="EQUIPMENT_WOODEN_CLUB"											Toughness="1"	Desirability="1" 	AntiPersonnel="27" ObsoleteTech="TECH_IRON_WORKING"	/>
		<Row ResourceType="EQUIPMENT_STONE_AXE"												Toughness="1"	Desirability="2" 	AntiPersonnel="27" ObsoleteTech="TECH_IRON_WORKING"	/>
		<Row ResourceType="EQUIPMENT_SPIKED_CLUB"	PrereqTech="TECH_BRONZE_WORKING"		Toughness="2"	Desirability="3" 	AntiPersonnel="32" AntiPersonnelArmor="10" ObsoleteTech="TECH_IRON_WORKING"	/>
		
		<Row ResourceType="EQUIPMENT_WOODEN_SPEARS"											Toughness="1"	Desirability="11" 	AntiPersonnel="27" ObsoleteTech="TECH_MILITARY_ENGINEERING"	/>
		<Row ResourceType="EQUIPMENT_BRONZE_SPEARS"	PrereqTech="TECH_BRONZE_WORKING"		Toughness="2"	Desirability="12" 	AntiPersonnel="32" AntiPersonnelArmor="4" ObsoleteTech="TECH_MILITARY_ENGINEERING"	/>
		<Row ResourceType="EQUIPMENT_IRON_SPEARS"	PrereqTech="TECH_IRON_WORKING"			Toughness="4"	Desirability="13" 	AntiPersonnel="40" AntiPersonnelArmor="6" ObsoleteTech="TECH_MILITARY_ENGINEERING"	/>
		
		<Row ResourceType="EQUIPMENT_BRONZE_SWORDS"	PrereqTech="TECH_BRONZE_WORKING"		Toughness="3"	Desirability="21" 	AntiPersonnel="38" AntiPersonnelArmor="5" />
		<Row ResourceType="EQUIPMENT_IRON_SWORDS"	PrereqTech="TECH_IRON_WORKING"			Toughness="5"	Desirability="22" 	AntiPersonnel="42" AntiPersonnelArmor="7" />
		<Row ResourceType="EQUIPMENT_STEEL_SWORDS"	PrereqTech="TECH_CASTLES"				Toughness="7"	Desirability="23" 	AntiPersonnel="46" AntiPersonnelArmor="10" />
		
		<Row ResourceType="EQUIPMENT_IRON_PIKES"	PrereqTech="TECH_MILITARY_ENGINEERING"	Toughness="6"	Desirability="30" 	AntiPersonnel="44" AntiPersonnelArmor="8" />
		<Row ResourceType="EQUIPMENT_STEEL_PIKES"	PrereqTech="TECH_MILITARY_ENGINEERING"	Toughness="7"	Desirability="35" 	AntiPersonnel="48" AntiPersonnelArmor="12" />
	</Equipment>
	
	<Equipment> <!-- Skirmisher Weapons -->		
		<Row ResourceType="EQUIPMENT_SLINGS"												Desirability="1" 	ObsoleteTech="TECH_ARCHERY"		/>
		<Row ResourceType="EQUIPMENT_WOODEN_BOWS"	PrereqTech="TECH_ARCHERY"				Desirability="10" 	ObsoleteTech="TECH_MACHINERY"	/>
		<Row ResourceType="EQUIPMENT_CROSSBOWS"		PrereqTech="TECH_MACHINERY"				Desirability="20" 	/>
	</Equipment>
	
	<Equipment>  <!-- Personnel Armor -->
		<Row ResourceType="EQUIPMENT_LEATHER_ARMOR"											Toughness="3"	Desirability="10" 	PersonnelArmor="20" />
		<Row ResourceType="EQUIPMENT_BRONZE_ARMOR"		PrereqTech="TECH_BRONZE_WORKING"	Toughness="5"	Desirability="20" 	PersonnelArmor="25" />
		<Row ResourceType="EQUIPMENT_IRON_ARMOR"		PrereqTech="TECH_IRON_WORKING"		Toughness="15"	Desirability="30" 	PersonnelArmor="35" />
		<Row ResourceType="EQUIPMENT_CHAINMAIL_ARMOR" 	PrereqTech="TECH_MACHINERY"			Toughness="20"	Desirability="40" 	PersonnelArmor="40" />
		<Row ResourceType="EQUIPMENT_PLATE_ARMOR"		PrereqTech="TECH_CASTLES"			Toughness="30"	Desirability="50" 	PersonnelArmor="50" />
	</Equipment>
	
	<Equipment>  <!-- "Vehicle" -->
		<Row ResourceType="EQUIPMENT_CHARIOT"			PrereqTech="TECH_THE_WHEEL"			Desirability="1" 	Size="20" ObsoleteTech="TECH_HORSEBACK_RIDING"	/>
		<Row ResourceType="EQUIPMENT_WAR_HORSES"		PrereqTech="TECH_HORSEBACK_RIDING"	Desirability="10" 	Size="10" />
		<Row ResourceType="EQUIPMENT_ARMORED_HORSES"	PrereqTech="TECH_STIRRUPS"			Desirability="20" 	Size="10" />
	</Equipment>
	
	<EquipmentClasses> <!-- Specific to Unit types -->
		<Row EquipmentClass="EQUIPMENTCLASS_MATERIEL"		/>
		<Row EquipmentClass="EQUIPMENTCLASS_BLUNT_WEAPONS"	/>
		<Row EquipmentClass="EQUIPMENTCLASS_SLINGS"			/>
		<Row EquipmentClass="EQUIPMENTCLASS_BOWS"			/>
		<Row EquipmentClass="EQUIPMENTCLASS_CROSSBOWS"		/>
		<Row EquipmentClass="EQUIPMENTCLASS_CHARIOT"		/>
		<Row EquipmentClass="EQUIPMENTCLASS_WAR_HORSES"		/>
		<Row EquipmentClass="EQUIPMENTCLASS_ARMORED_HORSES"	/>
		<Row EquipmentClass="EQUIPMENTCLASS_SPEARS"			/>
		<Row EquipmentClass="EQUIPMENTCLASS_SWORDS"			/>
		<Row EquipmentClass="EQUIPMENTCLASS_PIKES"			/>
		<Row EquipmentClass="EQUIPMENTCLASS_SHIELDS"		/>
		<Row EquipmentClass="EQUIPMENTCLASS_BODYARMOR"		/>
		<Row EquipmentClass="EQUIPMENTCLASS_HEAVYARMOR"		/>
		<Row EquipmentClass="EQUIPMENTCLASS_LIGHTARMOR"		/>
		<Row EquipmentClass="EQUIPMENTCLASS_HELMET"			/>
	</EquipmentClasses>
	
	<EquipmentClasses> <!-- Specific to promotion Class -->
		<Row EquipmentClass="EQUIPMENTCLASS_MELEE_WEAPON"		/>
		<Row EquipmentClass="EQUIPMENTCLASS_MELEE_ARMOR"		/>
		<Row EquipmentClass="EQUIPMENTCLASS_MELEE_SHIELD"		/>
		<Row EquipmentClass="EQUIPMENTCLASS_MELEE_HELMET"		/>
		<Row EquipmentClass="EQUIPMENTCLASS_SKIRMISHER_WEAPON"	/>
		<Row EquipmentClass="EQUIPMENTCLASS_SKIRMISHER_ARMOR"	/>
		<Row EquipmentClass="EQUIPMENTCLASS_CAVALRY_WEAPON"		/>
		<Row EquipmentClass="EQUIPMENTCLASS_CAVALRY_VEHICLE"	/>
	</EquipmentClasses>
	
	<EquipmentTypeClasses> <!-- Specific to Unit types -->
		<Row ResourceType="RESOURCE_MATERIEL"			EquipmentClass="EQUIPMENTCLASS_MATERIEL"	/>
		
		<Row ResourceType="EQUIPMENT_WOODEN_CLUB"		EquipmentClass="EQUIPMENTCLASS_BLUNT_WEAPONS"	/>
		<Row ResourceType="EQUIPMENT_STONE_AXE"			EquipmentClass="EQUIPMENTCLASS_BLUNT_WEAPONS"	/>
		<Row ResourceType="EQUIPMENT_SPIKED_CLUB"		EquipmentClass="EQUIPMENTCLASS_BLUNT_WEAPONS"	/>
		<Row ResourceType="EQUIPMENT_BRONZE_SWORDS"		EquipmentClass="EQUIPMENTCLASS_SWORDS"			/>
		<Row ResourceType="EQUIPMENT_IRON_SWORDS"		EquipmentClass="EQUIPMENTCLASS_SWORDS"			/>
		<Row ResourceType="EQUIPMENT_STEEL_SWORDS"		EquipmentClass="EQUIPMENTCLASS_SWORDS"			/>
		
		<Row ResourceType="EQUIPMENT_SLINGS"			EquipmentClass="EQUIPMENTCLASS_SLINGS"			/>
		<Row ResourceType="EQUIPMENT_WOODEN_BOWS"		EquipmentClass="EQUIPMENTCLASS_BOWS"			/>
		<Row ResourceType="EQUIPMENT_CROSSBOWS"			EquipmentClass="EQUIPMENTCLASS_CROSSBOWS"		/>
		
		<Row ResourceType="EQUIPMENT_CHARIOT"			EquipmentClass="EQUIPMENTCLASS_CHARIOT"			/>
		<Row ResourceType="EQUIPMENT_WAR_HORSES"		EquipmentClass="EQUIPMENTCLASS_WAR_HORSES"		/>
		<Row ResourceType="EQUIPMENT_ARMORED_HORSES"	EquipmentClass="EQUIPMENTCLASS_ARMORED_HORSES"	/>
		
		<Row ResourceType="EQUIPMENT_WOODEN_SPEARS"		EquipmentClass="EQUIPMENTCLASS_SPEARS"			/>
		<Row ResourceType="EQUIPMENT_BRONZE_SPEARS"		EquipmentClass="EQUIPMENTCLASS_SPEARS"			/>
		<Row ResourceType="EQUIPMENT_IRON_SPEARS"		EquipmentClass="EQUIPMENTCLASS_SPEARS"			/>
		
		<Row ResourceType="EQUIPMENT_IRON_PIKES"		EquipmentClass="EQUIPMENTCLASS_PIKES"			/>
		<Row ResourceType="EQUIPMENT_STEEL_PIKES"		EquipmentClass="EQUIPMENTCLASS_PIKES"			/>
		
		<Row ResourceType="EQUIPMENT_LEATHER_ARMOR"		EquipmentClass="EQUIPMENTCLASS_BODYARMOR"		/>
		<Row ResourceType="EQUIPMENT_BRONZE_ARMOR"		EquipmentClass="EQUIPMENTCLASS_BODYARMOR"		/>
		<Row ResourceType="EQUIPMENT_IRON_ARMOR"		EquipmentClass="EQUIPMENTCLASS_BODYARMOR"		/>
		<Row ResourceType="EQUIPMENT_CHAINMAIL_ARMOR"	EquipmentClass="EQUIPMENTCLASS_BODYARMOR"		/>
		<Row ResourceType="EQUIPMENT_CHAINMAIL_ARMOR"	EquipmentClass="EQUIPMENTCLASS_HEAVYARMOR"		/>
		<Row ResourceType="EQUIPMENT_IRON_ARMOR"		EquipmentClass="EQUIPMENTCLASS_HEAVYARMOR"		/>
		<Row ResourceType="EQUIPMENT_PLATE_ARMOR"		EquipmentClass="EQUIPMENTCLASS_HEAVYARMOR"		/>
		<Row ResourceType="EQUIPMENT_LEATHER_ARMOR"		EquipmentClass="EQUIPMENTCLASS_LIGHTARMOR"		/>
	</EquipmentTypeClasses>
	
	<EquipmentTypeClasses> <!-- Specific to promotion Class -->
		
		<Row ResourceType="EQUIPMENT_WOODEN_CLUB"		EquipmentClass="EQUIPMENTCLASS_MELEE_WEAPON"		/>
		<Row ResourceType="EQUIPMENT_STONE_AXE"			EquipmentClass="EQUIPMENTCLASS_MELEE_WEAPON"		/>
		<Row ResourceType="EQUIPMENT_SPIKED_CLUB"		EquipmentClass="EQUIPMENTCLASS_MELEE_WEAPON"		/>
		<Row ResourceType="EQUIPMENT_WOODEN_SPEARS"		EquipmentClass="EQUIPMENTCLASS_MELEE_WEAPON"		/>
		<Row ResourceType="EQUIPMENT_BRONZE_SPEARS"		EquipmentClass="EQUIPMENTCLASS_MELEE_WEAPON"		/>
		<Row ResourceType="EQUIPMENT_IRON_SPEARS"		EquipmentClass="EQUIPMENTCLASS_MELEE_WEAPON"		/>
		<Row ResourceType="EQUIPMENT_BRONZE_SWORDS"		EquipmentClass="EQUIPMENTCLASS_MELEE_WEAPON"		/>
		<Row ResourceType="EQUIPMENT_IRON_SWORDS"		EquipmentClass="EQUIPMENTCLASS_MELEE_WEAPON"		/>
		<Row ResourceType="EQUIPMENT_STEEL_SWORDS"		EquipmentClass="EQUIPMENTCLASS_MELEE_WEAPON"		/>
		<Row ResourceType="EQUIPMENT_IRON_PIKES"		EquipmentClass="EQUIPMENTCLASS_MELEE_WEAPON"		/>
		<Row ResourceType="EQUIPMENT_STEEL_PIKES"		EquipmentClass="EQUIPMENTCLASS_MELEE_WEAPON"		/>
		
		<Row ResourceType="EQUIPMENT_LEATHER_ARMOR"		EquipmentClass="EQUIPMENTCLASS_MELEE_ARMOR"			/>
		<Row ResourceType="EQUIPMENT_BRONZE_ARMOR"		EquipmentClass="EQUIPMENTCLASS_MELEE_ARMOR"			/>
		<Row ResourceType="EQUIPMENT_IRON_ARMOR"		EquipmentClass="EQUIPMENTCLASS_MELEE_ARMOR"			/>
		<Row ResourceType="EQUIPMENT_CHAINMAIL_ARMOR"	EquipmentClass="EQUIPMENTCLASS_MELEE_ARMOR"			/>
		<Row ResourceType="EQUIPMENT_PLATE_ARMOR"		EquipmentClass="EQUIPMENTCLASS_MELEE_ARMOR"			/>
		
		<Row ResourceType="EQUIPMENT_SLINGS"			EquipmentClass="EQUIPMENTCLASS_SKIRMISHER_WEAPON"	/>
		<Row ResourceType="EQUIPMENT_WOODEN_BOWS"		EquipmentClass="EQUIPMENTCLASS_SKIRMISHER_WEAPON"	/>
		<Row ResourceType="EQUIPMENT_CROSSBOWS"			EquipmentClass="EQUIPMENTCLASS_SKIRMISHER_WEAPON"	/>
		
		<Row ResourceType="EQUIPMENT_LEATHER_ARMOR"		EquipmentClass="EQUIPMENTCLASS_SKIRMISHER_ARMOR"	/>
		
		<Row ResourceType="EQUIPMENT_CHARIOT"			EquipmentClass="EQUIPMENTCLASS_CAVALRY_VEHICLE"		/>
		<Row ResourceType="EQUIPMENT_WAR_HORSES"		EquipmentClass="EQUIPMENTCLASS_CAVALRY_VEHICLE"		/>
		<Row ResourceType="EQUIPMENT_ARMORED_HORSES"	EquipmentClass="EQUIPMENTCLASS_CAVALRY_VEHICLE"		/>	
		
	</EquipmentTypeClasses>
	
	<EquipmentEffects> <!-- Not coded yet -->
		<Row ResourceType="EQUIPMENT_IRON_SWORDS"	EquipmentEffect="COMBAT_STRENGTH"	EffectMaxStrength="50" />
		<Row ResourceType="EQUIPMENT_STEEL_SWORDS"	EquipmentEffect="COMBAT_STRENGTH"	EffectMaxStrength="100" />
	</EquipmentEffects>	
	
	<UnitEquipmentClasses> <!-- Equipment Classes used by an Unit Type -->
		<Row UnitType="UNIT_SETTLER"				EquipmentClass="EQUIPMENTCLASS_MATERIEL" 		PercentageOfPersonnel="30" />
		<Row UnitType="UNIT_BUILDER"				EquipmentClass="EQUIPMENTCLASS_MATERIEL" 		PercentageOfPersonnel="100" />
		
		<Row UnitType="UNIT_SCOUT"					EquipmentClass="EQUIPMENTCLASS_MATERIEL" 		PercentageOfPersonnel="5" />
		
		<Row UnitType="UNIT_WARRIOR"				EquipmentClass="EQUIPMENTCLASS_MATERIEL" 		PercentageOfPersonnel="10" />
		<Row UnitType="UNIT_WARRIOR"				EquipmentClass="EQUIPMENTCLASS_BLUNT_WEAPONS" />
		<Row UnitType="UNIT_WARRIOR"				EquipmentClass="EQUIPMENTCLASS_BODYARMOR"		IsRequired="0" />
		<Row UnitType="UNIT_WARRIOR"				EquipmentClass="EQUIPMENTCLASS_HELMET"			IsRequired="0" />
		
		<Row UnitType="UNIT_SLINGER"				EquipmentClass="EQUIPMENTCLASS_MATERIEL" 		PercentageOfPersonnel="6" />
		<Row UnitType="UNIT_SLINGER"				EquipmentClass="EQUIPMENTCLASS_SLINGS" 			/>
		
		<Row UnitType="UNIT_ARCHER"					EquipmentClass="EQUIPMENTCLASS_MATERIEL" 		PercentageOfPersonnel="7" />
		<Row UnitType="UNIT_ARCHER"					EquipmentClass="EQUIPMENTCLASS_BOWS" />
		
		<Row UnitType="UNIT_CROSSBOWMAN"			EquipmentClass="EQUIPMENTCLASS_MATERIEL" 		PercentageOfPersonnel="10" />
		<Row UnitType="UNIT_CROSSBOWMAN"			EquipmentClass="EQUIPMENTCLASS_CROSSBOWS" />
		
		<Row UnitType="UNIT_HEAVY_CHARIOT"			EquipmentClass="EQUIPMENTCLASS_MATERIEL" 		PercentageOfPersonnel="15" />
		<Row UnitType="UNIT_HEAVY_CHARIOT"			EquipmentClass="EQUIPMENTCLASS_CHARIOT" 		PercentageOfPersonnel="25" />
		
		<Row UnitType="UNIT_BARBARIAN_HORSE_ARCHER"	EquipmentClass="EQUIPMENTCLASS_MATERIEL" 		PercentageOfPersonnel="10" />
		<Row UnitType="UNIT_BARBARIAN_HORSE_ARCHER"	EquipmentClass="EQUIPMENTCLASS_WAR_HORSES" />
		
		<Row UnitType="UNIT_BARBARIAN_HORSEMAN"		EquipmentClass="EQUIPMENTCLASS_MATERIEL" 		PercentageOfPersonnel="10" />
		<Row UnitType="UNIT_BARBARIAN_HORSEMAN"		EquipmentClass="EQUIPMENTCLASS_WAR_HORSES" />
		
		<Row UnitType="UNIT_HORSEMAN"				EquipmentClass="EQUIPMENTCLASS_MATERIEL" 		PercentageOfPersonnel="10" />
		<Row UnitType="UNIT_HORSEMAN"				EquipmentClass="EQUIPMENTCLASS_WAR_HORSES" />
		
		<Row UnitType="UNIT_KNIGHT"					EquipmentClass="EQUIPMENTCLASS_MATERIEL" 		PercentageOfPersonnel="15" />
		<Row UnitType="UNIT_KNIGHT"					EquipmentClass="EQUIPMENTCLASS_ARMORED_HORSES" />
		
		<Row UnitType="UNIT_SPEARMAN"				EquipmentClass="EQUIPMENTCLASS_MATERIEL" 		PercentageOfPersonnel="10" />
		<Row UnitType="UNIT_SPEARMAN"				EquipmentClass="EQUIPMENTCLASS_SPEARS" />
		<Row UnitType="UNIT_SPEARMAN"				EquipmentClass="EQUIPMENTCLASS_BODYARMOR"		IsRequired="0" />
		<Row UnitType="UNIT_SPEARMAN"				EquipmentClass="EQUIPMENTCLASS_HELMET"			IsRequired="0" />
		
		<Row UnitType="UNIT_SWORDSMAN"				EquipmentClass="EQUIPMENTCLASS_MATERIEL" 		PercentageOfPersonnel="10" />
		<Row UnitType="UNIT_SWORDSMAN"				EquipmentClass="EQUIPMENTCLASS_SWORDS" />
		<Row UnitType="UNIT_SWORDSMAN"				EquipmentClass="EQUIPMENTCLASS_SHIELDS"			IsRequired="0" />
		<Row UnitType="UNIT_SWORDSMAN"				EquipmentClass="EQUIPMENTCLASS_BODYARMOR"		IsRequired="0" />
		<Row UnitType="UNIT_SWORDSMAN"				EquipmentClass="EQUIPMENTCLASS_HELMET"			IsRequired="0" />
		
		<Row UnitType="UNIT_PIKEMAN"				EquipmentClass="EQUIPMENTCLASS_MATERIEL" 		PercentageOfPersonnel="10" />
		<Row UnitType="UNIT_PIKEMAN"				EquipmentClass="EQUIPMENTCLASS_PIKES" />
		<Row UnitType="UNIT_PIKEMAN"				EquipmentClass="EQUIPMENTCLASS_BODYARMOR"		IsRequired="0" />
		<Row UnitType="UNIT_PIKEMAN"				EquipmentClass="EQUIPMENTCLASS_HELMET"			IsRequired="0" />
		
		<Row UnitType="UNIT_GALLEY" 				EquipmentClass="EQUIPMENTCLASS_MATERIEL" 		PercentageOfPersonnel="100" />
		<Row UnitType="UNIT_QUADRIREME" 			EquipmentClass="EQUIPMENTCLASS_MATERIEL" 		PercentageOfPersonnel="105" />
		<Row UnitType="UNIT_CARAVEL" 				EquipmentClass="EQUIPMENTCLASS_MATERIEL" 		PercentageOfPersonnel="150" />
		<Row UnitType="UNIT_PRIVATEER" 				EquipmentClass="EQUIPMENTCLASS_MATERIEL" 		PercentageOfPersonnel="155" />
		<Row UnitType="UNIT_FRIGATE" 				EquipmentClass="EQUIPMENTCLASS_MATERIEL" 		PercentageOfPersonnel="160" />
		<Row UnitType="UNIT_IRONCLAD" 				EquipmentClass="EQUIPMENTCLASS_MATERIEL" 		PercentageOfPersonnel="175" />
		<Row UnitType="UNIT_DESTROYER" 				EquipmentClass="EQUIPMENTCLASS_MATERIEL" 		PercentageOfPersonnel="200" />
		<Row UnitType="UNIT_SUBMARINE" 				EquipmentClass="EQUIPMENTCLASS_MATERIEL" 		PercentageOfPersonnel="200" />
		<Row UnitType="UNIT_NUCLEAR_SUBMARINE"		EquipmentClass="EQUIPMENTCLASS_MATERIEL" 		PercentageOfPersonnel="300" />
		<Row UnitType="UNIT_BATTLESHIP" 			EquipmentClass="EQUIPMENTCLASS_MATERIEL" 		PercentageOfPersonnel="350" />
		<Row UnitType="UNIT_AIRCRAFT_CARRIER" 		EquipmentClass="EQUIPMENTCLASS_MATERIEL" 		PercentageOfPersonnel="350" />
		<Row UnitType="UNIT_MISSILE_CRUISER" 		EquipmentClass="EQUIPMENTCLASS_MATERIEL" 		PercentageOfPersonnel="375" />
		
	</UnitEquipmentClasses>
	
	<UnitConstructionResources>
		
		<Row UnitType="UNIT_GALLEY" 			ResourceType="RESOURCE_WOOD" 	Quantity="200" />
		<Row UnitType="UNIT_QUADRIREME" 		ResourceType="RESOURCE_WOOD" 	Quantity="300" />
		<Row UnitType="UNIT_CARAVEL" 			ResourceType="RESOURCE_WOOD" 	Quantity="400" />
		<Row UnitType="UNIT_PRIVATEER" 			ResourceType="RESOURCE_WOOD" 	Quantity="450" />
		<Row UnitType="UNIT_FRIGATE" 			ResourceType="RESOURCE_WOOD" 	Quantity="600" />
		<Row UnitType="UNIT_IRONCLAD" 			ResourceType="RESOURCE_STEEL" 	Quantity="100" />
		<Row UnitType="UNIT_DESTROYER" 			ResourceType="RESOURCE_STEEL" 	Quantity="300" />
		<Row UnitType="UNIT_SUBMARINE" 			ResourceType="RESOURCE_STEEL" 	Quantity="300" />
		<Row UnitType="UNIT_NUCLEAR_SUBMARINE"	ResourceType="RESOURCE_STEEL" 	Quantity="900" />
		<Row UnitType="UNIT_BATTLESHIP" 		ResourceType="RESOURCE_STEEL" 	Quantity="1200" />
		<Row UnitType="UNIT_AIRCRAFT_CARRIER" 	ResourceType="RESOURCE_STEEL" 	Quantity="1500" />
		<Row UnitType="UNIT_MISSILE_CRUISER" 	ResourceType="RESOURCE_STEEL" 	Quantity="1000" />
		
	</UnitConstructionResources>
	
	<PromotionClassEquipmentClasses> <!-- Equipment Classes representing an Upgrade Line -->
		<Row PromotionClassType="PROMOTION_CLASS_MELEE"			EquipmentClass="EQUIPMENTCLASS_MATERIEL" 			/>
		<Row PromotionClassType="PROMOTION_CLASS_MELEE"			EquipmentClass="EQUIPMENTCLASS_MELEE_WEAPON" 		/>
		<Row PromotionClassType="PROMOTION_CLASS_MELEE"			EquipmentClass="EQUIPMENTCLASS_MELEE_SHIELD"		IsRequired="0" />
		<Row PromotionClassType="PROMOTION_CLASS_MELEE"			EquipmentClass="EQUIPMENTCLASS_MELEE_ARMOR"			IsRequired="0" />
		<Row PromotionClassType="PROMOTION_CLASS_MELEE"			EquipmentClass="EQUIPMENTCLASS_MELEE_HELMET"		IsRequired="0" />
		<Row PromotionClassType="PROMOTION_CLASS_SKIRMISHER"	EquipmentClass="EQUIPMENTCLASS_MATERIEL" 			/>
		<Row PromotionClassType="PROMOTION_CLASS_SKIRMISHER"	EquipmentClass="EQUIPMENTCLASS_SKIRMISHER_WEAPON" 	/>
		<Row PromotionClassType="PROMOTION_CLASS_SKIRMISHER"	EquipmentClass="EQUIPMENTCLASS_SKIRMISHER_ARMOR"	IsRequired="0" />
		<Row PromotionClassType="PROMOTION_CLASS_CAVALRY"		EquipmentClass="EQUIPMENTCLASS_MATERIEL" 			/>
		<Row PromotionClassType="PROMOTION_CLASS_CAVALRY"		EquipmentClass="EQUIPMENTCLASS_CAVALRY_VEHICLE" 	/>
	</PromotionClassEquipmentClasses>
	
</GameInfo>
